dsp_ingest/__init__.py
dsp_ingest/__main__.py
dsp_ingest/ingest.py
dsp_ingest/follow_logs/__init__.py
dsp_ingest/follow_logs/post_events.py
dsp_ingest/get_args/__init__.py
dsp_ingest/get_args/cli.py
dsp_ingest/log_gen/__init__.py
dsp_ingest/log_gen/parse_configs.py
dsp_ingest/purge_logs/__init__.py
dsp_ingest/purge_logs/purge.py
dsp_ingest/validate_args/__init__.py
dsp_ingest/validate_args/validate.py
dspingest-1.1.2.dist-info/METADATA
dspingest-1.1.2.dist-info/WHEEL
dspingest-1.1.2.dist-info/top_level.txt
dspingest-1.1.2.dist-info/RECORD
